{
  "themes": [
    {
      "id": 1,
      "name": "Learning tools",
      "vietsub": "Dụng cụ học tập",
      "image": "https://www.flaticon.com/premium-icon/icons/svg/3940/3940097.svg"
    },
    {
      "id": 2,
      "name": "Fruits",
      "vietsub": "Trái cây",
      "image": "https://www.flaticon.com/premium-icon/icons/svg/528/528407.svg"
    },
    {
      "id": 3,
      "name": "Animal",
      "vietsub": "Động vật",
      "image": "https://www.flaticon.com/premium-icon/icons/svg/449/449631.svg"
    },
    {
      "id": 4,
      "name": "Accessories",
      "vietsub": "Phụ kiện",
      "image": "https://www.flaticon.com/premium-icon/icons/svg/512/3659892.svg" 
    }
    
  ],
  "vocabulary": [
    {
      "key": 1,
      "nameEn": "Pen",
      "nameVn": "Bút mực",
      "IPA": "[pen]",
      "categorie": 1,
      "image": "https://www.flaticon.com/premium-icon/icons/svg/937/937159.svg",
      "url": "https://www.collinsdictionary.com/sounds/hwd_sounds/39419.mp3",
      "exEn1": "Pencil",
      "exVn1": "Bút chì",
      "others": [
        ""
      ]
    },
    {
      "key": 2,
      "nameEn": "Paper",
      "nameVn": "Giấy",
      "IPA": "[pāpər]",
      "categorie": 1,
      "image": "https://www.flaticon.com/premium-icon/icons/svg/3073/3073464.svg",
      "url": "https://www.collinsdictionary.com/sounds/hwd_sounds/38615.mp3",
      "exEn1": "",
      "exVn1": "",
      "exEn2": "",
      "exVn2": "",
      "others": [
        ""
      ]
    },
    {
      "key": 3,
      "nameEn": "Glue",
      "nameVn": "Keo dán",
      "IPA": "[ɡlo͞o]",
      "categorie": 1,
      "image": "https://www.flaticon.com/premium-icon/icons/svg/2655/2655812.svg",
      "url": "https://www.collinsdictionary.com/sounds/hwd_sounds/23899.mp3",
      "exEn1": "gummy",
      "exVn1": "kẹo dẻo",
      "exEn2": "",
      "exVn2": "",
      "others": [
        ""
      ]
    },
    {
      "key": 4,
      "nameEn": "Book",
      "nameVn": "Sách",
      "IPA": "[bo͝ok̃]",
      "categorie": 1,
      "image": "https://www.flaticon.com/premium-icon/icons/svg/3145/3145765.svg",
      "url": "https://www.collinsdictionary.com/sounds/hwd_sounds/05846.mp3",
      "exEn1": "Note",
      "exVn1": "Ghi chú",
      "exEn2": "Record",
      "exVn2": "Ghi lại",
      "others": [
        ""
      ]
    },
     {
      "key": 12,
      "nameEn": "Marker",
      "nameVn": "Bút lông",
      "IPA": "[ˈmärkər]",
      "categorie": 1,
      "image": "https://www.flaticon.com/premium-icon/icons/svg/1142/1142596.svg",
      "url": "https://www.collinsdictionary.com/sounds/hwd_sounds/33229.mp3",
      "exEn1": "Note",
      "exVn1": "Ghi chú",
      "exEn2": "Record",
      "exVn2": "Ghi lại",
      "others": [
        ""
      ]
    },
    {
      "key": 20,
      "nameEn": "Ruler",
      "nameVn": "Thước",
      "IPA": "[̃ˈro͞olər]",
      "categorie": 1,
      "image": "https://www.flaticon.com/premium-icon/icons/svg/186/186278.svg",
      "url": "https://www.collinsdictionary.com/sounds/hwd_sounds/47461.mp3",
      "exEn1": "",
      "exVn1": "",
      "exEn2": "",
      "exVn2": "",
      "others": [
        ""
      ]
    },
    {
      "key": 5,
      "nameEn": "Pineapple",
      "nameVn": "Trái dứa",
      "IPA": "[pīˌnapəl]",
      "categorie": 2,
      "image": "https://www.flaticon.com/premium-icon/icons/svg/3151/3151121.svg",
      "url": "https://www.collinsdictionary.com/sounds/hwd_sounds/40436.mp3",
      "exEn1": "",
      "exVn1": "",
      "exEn2": "",
      "exVn2": "",
      "others": [
        ""
      ]
    },
    
    {
      "key": 6,
      "nameEn": "Apple",
      "nameVn": "Trái táo",
      "IPA": "[ˈapəl]",
      "categorie": 2,
      "image": "https://cdn3.iconfinder.com/data/icons/unigrid-flat-fruits-vegetables/90/010_008_apple_fruit_food-256.png",
      "url": "https://www.collinsdictionary.com/sounds/hwd_sounds/02214.mp3",
      "exEn1": "",
      "exVn1": "",
      "exEn2": "",
      "exVn2": "",
      "others": [
        ""
      ]
    },
    {
      "key": 7,
      "nameEn": "Banana",
      "nameVn": "Trái chuối",
      "IPA": "[bəˈnanə]",
      "categorie": 2,
      "image": "https://cdn2.iconfinder.com/data/icons/food-98/64/Food_banana-256.png",
      "url": "https://www.collinsdictionary.com/sounds/hwd_sounds/03673.mp3",
      "exEn1": "",
      "exVn1": "",
      "exEn2": "",
      "exVn2": "",
      "others": [
        ""
      ]
    },
     {
      "key": 15,
      "nameEn": "Orange",
      "nameVn": "Trái cam",
      "IPA": "[ɒrɪndʒ]",
      "categorie": 2,
      "image": "https://www.flaticon.com/premium-icon/icons/svg/1791/1791312.svg",
      "url": "https://www.collinsdictionary.com/sounds/hwd_sounds/37482.mp3",
      "exEn1": "",
      "exVn1": "",
      "exEn2": "",
      "exVn2": "",
      "others": [
        ""
      ]
    },
     {
      "key": 16,
      "nameEn": "Guava",
      "nameVn": "Trái ổi",
      "IPA": "[gwɑːvə]",
      "categorie": 2,
      "image": "https://www.flaticon.com/premium-icon/icons/svg/2690/2690186.svg",
      "url": "https://www.collinsdictionary.com/sounds/hwd_sounds/24837.mp3",
      "exEn1": "",
      "exVn1": "",
      "exEn2": "",
      "exVn2": "",
      "others": [
        ""
      ]
    },
    {
      "key": 8,
      "nameEn": "giraffe",
      "nameVn": "Hươu cao cổ",
      "IPA": "[jəˈraf]",
      "categorie": 3,
      "image": "https://www.flaticon.com/premium-icon/icons/svg/3065/3065712.svg",
      "url": "https://www.collinsdictionary.com/sounds/hwd_sounds/23668.mp3",
      "exEn1": "",
      "exVn1": "",
      "exEn2": "",
      "exVn2": "",
      "others": [
        
      ]
    },
    {
      "key": 9,
      "nameEn": "Gorillas",
      "nameVn": "Khỉ đột",
      "IPA": "[gərɪlə]",
      "categorie": 3,
      "image": "https://www.flaticon.com/premium-icon/icons/svg/2559/2559425.svg",
      "url": "https://www.collinsdictionary.com/sounds/hwd_sounds/24187.mp3",
      "exEn1": "",
      "exVn1": "",
      "exEn2": "",
      "exVn2": "",
      "others": [
        ""
      ]
    },
    {
      "key": 10,
      "nameEn": "Rabbit",
      "nameVn": "Thỏ",
      "IPA": "[ˈrabət̃]",
      "categorie": 3,
      "image": "https://www.flaticon.com/premium-icon/icons/svg/2716/2716961.svg",
      "url": "https://www.collinsdictionary.com/sounds/hwd_sounds/43904.mp3",
      "exEn1": "",
      "exVn1": "",
      "exEn2": "",
      "exVn2": "",
      "others": [
        ""
      ]
    },
    {
      "key": 11,
      "nameEn": "Horse",
      "nameVn": "Ngựa",
      "IPA": "[hɔːʳs]",
      "categorie": 3,
      "image": "https://www.flaticon.com/premium-icon/icons/svg/3042/3042491.svg",
      "url": "https://www.collinsdictionary.com/sounds/hwd_sounds/26795.mp3",
      "exEn1": "",
      "exVn1": "",
      "exEn2": "",
      "exVn2": "",
      "others": [
        ""
      ]
    },
    {
      "key": 13,
      "nameEn": "Wolf",
      "nameVn": "Chó sói",
      "IPA": "[wʊlf]",
      "categorie": 3,
      "image": "https://www.flaticon.com/premium-icon/icons/svg/165/165191.svg",
      "url": "https://www.collinsdictionary.com/sounds/hwd_sounds/FR-W0100460.mp3",
      "exEn1": "",
      "exVn1": "",
      "exEn2": "",
      "exVn2": "",
      "others": [
        ""
      ]
    },
       "key": 14,
      "nameEn": "belt",
      "nameVn": "thắt lưng",
      "IPA": "[belt]",
      "categorie": 4,
      "image": "https://www.flaticon.com/premium-icon/icons/svg/512/2777903.svg",
      "url": "https://www.collinsdictionary.com/sounds/hwd_sounds/04599.mp3",
      "exEn1": "",
      "exVn1": "",
      "exEn2": "",
      "exVn2": "",
      "others": [
        ""
      ]
    },
     {
      "key": 17,
     "nameEn": "bag",
      "nameVn": "túi",
      "IPA": "[bæg]",
      "categorie": 4,
      "image": "https://www.flaticon.com/premium-icon/icons/svg/512/2822424.svg",
      "url": "https://www.collinsdictionary.com/sounds/hwd_sounds/03508.mp3",
      "exEn1": "",
      "exVn1": "",
      "exEn2": "",
      "exVn2": "",
      "others": [
        ""
      ]
    },
       {
      "key": 18,
      "nameEn": "earring",
      "nameVn": "bông tai",
      "IPA": "[ɪərɪŋ]",
      "categorie": 4,
      "image": "https://www.flaticon.com/premium-icon/icons/svg/512/2954566.svg",
      "url": "https://www.collinsdictionary.com/sounds/hwd_sounds/17704.mp3",
      "exEn1": "",
      "exVn1": "",
      "exEn2": "",
      "exVn2": "",
      "others": [
        ""
      ]
    },
      {
      "key": 19,
      "nameEn": "glasses",
      "nameVn": "kính",
      "IPA": "[ˈɡlɑːsɪz]",
      "categorie": 4,
      "image": "https://www.flaticon.com/premium-icon/icons/svg/512/2763295.svg",
      "url": "https://www.collinsdictionary.com/sounds/hwd_sounds/en_gb_glasses.mp3",
      "exEn1": "",
      "exVn1": "",
      "exEn2": "",
      "exVn2": "",
      "others": [
        ""
      ]
    },
      {
      "key": 21,
     "nameEn": "bracelet",
      "nameVn": "vòng đeo tay",
      "IPA": "[breɪslɪt]",
      "categorie": 4,
      "image": "https://www.flaticon.com/premium-icon/icons/svg/128/2543937.svg",
      "url": "https://www.collinsdictionary.com/sounds/hwd_sounds/06176.mp3",
      "exEn1": "",
      "exVn1": "",
      "exEn2": "",
      "exVn2": "",
      "others": [
        ""
      ]
    },
   
        {
      "key": 22,
      "nameEn": "hat",
      "nameVn": "mũ",
      "IPA": "[hæt]",
      "categorie": 4,
      "image": "https://www.flaticon.com/premium-icon/icons/svg/128/3258179.svg",
      "url": "https://www.collinsdictionary.com/sounds/hwd_sounds/25589.mp3",
      "exEn1": "",
      "exVn1": "",
      "exEn2": "",
      "exVn2": "",
      "others": [
        ""
      ]
    },
       {
      "key": 23,
      "nameEn": "cap",
      "nameVn": "mũ lưỡi trai",
      "IPA": "[kæp]",
      "categorie": 4,
      "image": "https://www.flaticon.com/premium-icon/icons/svg/128/788067.svg",
      "url": "https://www.collinsdictionary.com/sounds/hwd_sounds/07743.mp3",
      "exEn1": "",
      "exVn1": "",
      "exEn2": "",
      "exVn2": "",
      "others": [
        ""
      ]
    },
     {
      "key": 24,
      "nameEn": "rucksack",
      "nameVn": "ba lô",
      "IPA": "[rʌksæk]",
      "categorie": 4,
      "image": "https://www.flaticon.com/premium-icon/icons/svg/128/2378448.svg",
      "url": "https://www.collinsdictionary.com/sounds/hwd_sounds/47408.mp3",
      "exEn1": "",
      "exVn1": "",
      "exEn2": "",
      "exVn2": "",
      "others": [
        ""
      ]
    },
     {
      "key": 25,
      "nameEn": "gloves",
      "nameVn": "găng tay",
      "IPA": "[glʌv]",
      "categorie": 4,
      "image": "https://www.flaticon.com/premium-icon/icons/svg/128/2832115.svg",
      "url": "https://www.collinsdictionary.com/sounds/hwd_sounds/23883.mp3",
      "exEn1": "",
      "exVn1": "",
      "exEn2": "",
      "exVn2": "",
      "others": [
        ""
      ]
    }
  ]
}
